luk_sdk/__init__.py
luk_sdk/sdk.py
luk_sdk-0.0.7.dist-info/METADATA
luk_sdk-0.0.7.dist-info/WHEEL
luk_sdk-0.0.7.dist-info/licenses/LICENSE
luk_sdk-0.0.7.dist-info/RECORD
