Metadata-Version: 2.3
Name: luk-sdk
Version: 0.0.7
Summary: LUKSDK
Project-URL: Homepage, https://github.com/CFGameTech/project-luksdk-python3
Project-URL: Issues, https://github.com/CFGameTech/project-luksdk-python3/issues
Author-email: LUKSDK <developer@luk.live>
Classifier: License :: OSI Approved :: MIT License
Classifier: Operating System :: OS Independent
Classifier: Programming Language :: Python :: 3
Requires-Python: >=3.8
